{"movies":[{"id":2,"name":"The Pursuit Of Happyness","price":14,"bannedCountries":[],"availableAmount":3,"totalAmount":5,"additionalProperties":{}},{"id":3,"name":"The Notebook","price":5,"bannedCountries":[],"availableAmount":0,"totalAmount":1,"additionalProperties":{}},{"id":4,"name":"Justice League","price":17,"bannedCountries":["jordan","iran","lebanon"],"availableAmount":3,"totalAmount":4,"additionalProperties":{}},{"id":5,"name":"The book of FIRE","price":117,"bannedCountries":["Israel","USA","Russia"],"availableAmount":3,"totalAmount":3,"additionalProperties":{}}],"additionalProperties":{}}